airflow/providers/git/__init__.py
airflow/providers/git/get_provider_info.py
airflow/providers/git/version_compat.py
airflow/providers/git/bundles/__init__.py
airflow/providers/git/bundles/git.py
airflow/providers/git/hooks/__init__.py
airflow/providers/git/hooks/git.py
apache_airflow_providers_git-0.2.1.dist-info/entry_points.txt
apache_airflow_providers_git-0.2.1.dist-info/licenses/LICENSE
apache_airflow_providers_git-0.2.1.dist-info/licenses/NOTICE
apache_airflow_providers_git-0.2.1.dist-info/WHEEL
apache_airflow_providers_git-0.2.1.dist-info/METADATA
apache_airflow_providers_git-0.2.1.dist-info/RECORD
