Metadata-Version: 2.4
Name: apache-airflow-providers-git
Version: 0.2.1
Summary: Provider package apache-airflow-providers-git for Apache Airflow
Keywords: airflow-provider,git,airflow,integration
Author-email: Apache Software Foundation <dev@airflow.apache.org>
Maintainer-email: Apache Software Foundation <dev@airflow.apache.org>
Requires-Python: >=3.10
License-Expression: Apache-2.0
Classifier: Development Status :: 5 - Production/Stable
Classifier: Environment :: Console
Classifier: Environment :: Web Environment
Classifier: Intended Audience :: Developers
Classifier: Intended Audience :: System Administrators
Classifier: Framework :: Apache Airflow
Classifier: Framework :: Apache Airflow :: Provider
Classifier: Programming Language :: Python :: 3.10
Classifier: Programming Language :: Python :: 3.11
Classifier: Programming Language :: Python :: 3.12
Classifier: Programming Language :: Python :: 3.13
Classifier: Topic :: System :: Monitoring
License-File: LICENSE
License-File: NOTICE
Requires-Dist: apache-airflow>=3.0.0
Requires-Dist: apache-airflow-providers-common-compat>=1.10.1
Requires-Dist: GitPython>=3.1.44
Project-URL: Bug Tracker, https://github.com/apache/airflow/issues
Project-URL: Changelog, https://airflow.apache.org/docs/apache-airflow-providers-git/0.2.1/changelog.html
Project-URL: Documentation, https://airflow.apache.org/docs/apache-airflow-providers-git/0.2.1
Project-URL: Mastodon, https://fosstodon.org/@airflow
Project-URL: Slack Chat, https://s.apache.org/airflow-slack
Project-URL: Source Code, https://github.com/apache/airflow
Project-URL: YouTube, https://www.youtube.com/channel/UCSXwxpWZQ7XZ1WL3wqevChA/
